{
  "model_type": "rf",
  "n_estimators": 300,
  "max_depth": 25,
  "min_samples_split": 10,
  "min_samples_leaf": 4,
  "feature_columns": [
    "经度",
    "纬度",
    "到市中心距离_km",
    "区域编码",
    "面积（m²）",
    "室数",
    "厅数",
    "卫数",
    "总房间数",
    "每室面积",
    "总楼层数",
    "当前楼层估算",
    "楼层比例",
    "朝向评分",
    "房龄",
    "小区面积_数值",
    "小区户数_数值",
    "容积率_数值",
    "绿化率_数值",
    "物业费_数值",
    "area_encoded",
    "面积_平方",
    "面积_立方",
    "面积_平方根",
    "面积_对数",
    "面积_小户型",
    "面积_中户型",
    "面积_大户型",
    "面积_豪宅",
    "距离_平方",
    "距离_倒数",
    "距离_对数",
    "距离_核心区",
    "距离_内环",
    "距离_中环",
    "距离_外环",
    "房龄_平方",
    "房龄_对数",
    "房龄_较新",
    "房龄_中等",
    "房龄_老旧",
    "面积_距离_交互",
    "面积_距离倒数_交互",
    "面积对数_距离对数_交互",
    "面积_房龄_交互",
    "面积对数_房龄对数_交互",
    "距离_房龄_交互",
    "面积_距离_房龄_三维交互",
    "户型_室厅比",
    "户型_厅室和",
    "楼层_中间度",
    "楼层_黄金层",
    "小区品质_综合",
    "经纬度_交互",
    "到中心_欧式距离",
    "面积（m²）_标准化",
    "到市中心距离_km_标准化",
    "房龄_标准化",
    "面积_平方_标准化",
    "距离_平方_标准化",
    "房龄_平方_标准化",
    "面积_距离_交互_标准化",
    "面积_房龄_交互_标准化"
  ],
  "area_encoder": {
    "东城": 0,
    "丰台": 1,
    "北京周边": 2,
    "城区": 3,
    "大兴": 4,
    "宣武": 5,
    "密云": 6,
    "崇文": 7,
    "平谷": 8,
    "延庆": 9,
    "怀柔": 10,
    "房山": 11,
    "昌平": 12,
    "朝阳": 13,
    "海淀": 14,
    "玄武区": 15,
    "石景山": 16,
    "西城": 17,
    "通州": 18,
    "门头沟": 19,
    "顺义": 20,
    "龙都街道": 21
  },
  "feature_importance": [
    {
      "feature": "纬度",
      "importance": 0.07493334980937685
    },
    {
      "feature": "到中心_欧式距离",
      "importance": 0.06985868934894579
    },
    {
      "feature": "区域编码",
      "importance": 0.06963093874188137
    },
    {
      "feature": "area_encoded",
      "importance": 0.06604496746455474
    },
    {
      "feature": "经度",
      "importance": 0.0646365185133073
    },
    {
      "feature": "经纬度_交互",
      "importance": 0.06248174961722919
    },
    {
      "feature": "到市中心距离_km_标准化",
      "importance": 0.05739760068589049
    },
    {
      "feature": "距离_倒数",
      "importance": 0.05555062330707006
    },
    {
      "feature": "距离_平方",
      "importance": 0.05496703225968234
    },
    {
      "feature": "到市中心距离_km",
      "importance": 0.052283415172515474
    },
    {
      "feature": "距离_对数",
      "importance": 0.051005332831713136
    },
    {
      "feature": "距离_平方_标准化",
      "importance": 0.04968357157334931
    },
    {
      "feature": "物业费_数值",
      "importance": 0.022122734496884
    },
    {
      "feature": "面积对数_距离对数_交互",
      "importance": 0.02153398448741222
    },
    {
      "feature": "面积_距离倒数_交互",
      "importance": 0.020848049014278548
    },
    {
      "feature": "面积_距离_交互",
      "importance": 0.01607831754360405
    },
    {
      "feature": "距离_房龄_交互",
      "importance": 0.014013133914533848
    },
    {
      "feature": "距离_外环",
      "importance": 0.013050210557363563
    },
    {
      "feature": "面积_距离_交互_标准化",
      "importance": 0.011701750787948086
    },
    {
      "feature": "小区面积_数值",
      "importance": 0.00886710446053767
    },
    {
      "feature": "小区户数_数值",
      "importance": 0.008623167704711818
    },
    {
      "feature": "小区品质_综合",
      "importance": 0.008448117504655269
    },
    {
      "feature": "容积率_数值",
      "importance": 0.007526204942233681
    },
    {
      "feature": "房龄_平方_标准化",
      "importance": 0.0070670217372841284
    },
    {
      "feature": "房龄_标准化",
      "importance": 0.0069896439153331906
    },
    {
      "feature": "房龄",
      "importance": 0.0069172490769623925
    },
    {
      "feature": "房龄_对数",
      "importance": 0.006811897467555299
    },
    {
      "feature": "房龄_平方",
      "importance": 0.006760728276787021
    },
    {
      "feature": "绿化率_数值",
      "importance": 0.006245008388840921
    },
    {
      "feature": "面积_距离_房龄_三维交互",
      "importance": 0.005664557638020909
    }
  ],
  "training_date": "2025-10-31 20:31:48",
  "train_samples": 37701,
  "test_samples": 4200,
  "train_r2": 0.9677280229082038,
  "test_r2": 0.7532849517412457,
  "test_rmse": 13202.382498291114,
  "scaler_info": {
    "means": {
      "经度": 116.40144514858238,
      "纬度": 39.92632544603742,
      "到市中心距离_km": 14.691529448751668,
      "区域编码": 10.914299355454762,
      "面积（m²）": 83.58809103206812,
      "室数": 2.110241650972174,
      "厅数": 1.168274881775688,
      "卫数": null,
      "总房间数": 3.308367274417079,
      "每室面积": 41.09710317534001,
      "总楼层数": 13.435373067027399,
      "当前楼层估算": 7.281008921542903,
      "楼层比例": 0.5042410128575178,
      "朝向评分": 3.943717443780968,
      "房龄": 23.520976548134318,
      "小区面积_数值": 785284.3284506793,
      "小区户数_数值": 2397.1577424023153,
      "容积率_数值": 2.2011339984650804,
      "绿化率_数值": 30.927555164285916,
      "物业费_数值": 1.6352327336041785,
      "area_encoded": 10.914299355454762,
      "面积_平方": 8262.701415750245,
      "面积_立方": 1001756.2370674548,
      "面积_平方根": 8.968987147527958,
      "面积_对数": 4.3647635782245775,
      "面积_小户型": 0.2683748441685897,
      "面积_中户型": 0.40969735550781144,
      "面积_大户型": 0.2558022333625103,
      "面积_豪宅": 0.06612556696108857,
      "距离_平方": 439.4804814065652,
      "距离_倒数": 0.10271285430958145,
      "距离_对数": 2.5769365357785743,
      "距离_核心区": 0.07917561868385455,
      "距离_内环": 0.30399724145248136,
      "距离_中环": 0.39399485424789793,
      "距离_外环": 0.22283228561576615,
      "房龄_平方": 645.6697784944412,
      "房龄_对数": 3.11834539098748,
      "房龄_次新房": 0.0,
      "房龄_较新": 0.023341555926898492,
      "房龄_中等": 0.28882523009999733,
      "房龄_老旧": 0.6254476008593937,
      "面积_距离_交互": 1278.0397158540736,
      "面积_距离倒数_交互": 8.171711311632349,
      "面积对数_距离对数_交互": 11.292555685408862,
      "面积_房龄_交互": 1893.9027468952447,
      "面积对数_房龄对数_交互": 13.589069341666587,
      "距离_房龄_交互": 315.5063451693299,
      "面积_距离_房龄_三维交互": 26648.389203678566,
      "户型_室厅比": 0.9921621153723496,
      "户型_厅室和": 3.308367274417079,
      "楼层_中间度": 0.6694873892302315,
      "楼层_顶底惩罚": 0.0,
      "楼层_黄金层": 0.3888225776504602,
      "小区品质_综合": 15.434316425421692,
      "经纬度_交互": 4647.48538205442,
      "到中心_欧式距离": 0.1520732186769097
    },
    "stds": {
      "经度": 0.13839712169399399,
      "纬度": 0.15418134217506005,
      "到市中心距离_km": 14.954777696233633,
      "区域编码": 5.910818434709594,
      "面积（m²）": 35.71787077111481,
      "室数": 0.7674929697442271,
      "厅数": 0.3843509499397815,
      "卫数": null,
      "总房间数": 0.974081994906132,
      "每室面积": 12.06652568880559,
      "总楼层数": 7.826012169989426,
      "当前楼层估算": 5.432525978802815,
      "楼层比例": 0.21612601613604696,
      "朝向评分": 1.2009285751245409,
      "房龄": 9.614367148797596,
      "小区面积_数值": 14667303.110835548,
      "小区户数_数值": 3643.466113535391,
      "容积率_数值": 0.8784621287303487,
      "绿化率_数值": 7.539626455697174,
      "物业费_数值": 1.2189816229256996,
      "area_encoded": 5.910818434709594,
      "面积_平方": 9327.108078363875,
      "面积_立方": 2645977.6678431565,
      "面积_平方根": 1.7735399659611641,
      "面积_对数": 0.37281924756021584,
      "面积_小户型": 0.4431196174885982,
      "面积_中户型": 0.4917843504992043,
      "面积_大户型": 0.43631697228478894,
      "面积_豪宅": 0.2485047572284001,
      "距离_平方": 9800.08608092024,
      "距离_倒数": 0.08454010040547143,
      "距离_对数": 0.5832739007347173,
      "距离_核心区": 0.2700162475821053,
      "距离_内环": 0.4599875334406055,
      "距离_中环": 0.48864019718780616,
      "距离_外环": 0.41615219774195933,
      "房龄_平方": 523.9019780719597,
      "房龄_对数": 0.4140289706185535,
      "房龄_次新房": 0.0,
      "房龄_较新": 0.1509878550796295,
      "房龄_中等": 0.4532225336100504,
      "房龄_老旧": 0.48401354661686263,
      "面积_距离_交互": 1562.84678834392,
      "面积_距离倒数_交互": 7.703173351904092,
      "面积对数_距离对数_交互": 2.891960008258008,
      "面积_房龄_交互": 932.5836366192906,
      "面积对数_房龄对数_交互": 1.9073740701247754,
      "距离_房龄_交互": 234.67585482369063,
      "面积_距离_房龄_三维交互": 23584.43932584665,
      "户型_室厅比": 0.32596627503761266,
      "户型_厅室和": 0.974081994906132,
      "楼层_中间度": 0.23953052530418847,
      "楼层_顶底惩罚": 0.0,
      "楼层_黄金层": 0.48748936829111206,
      "小区品质_综合": 7.896425035589279,
      "经纬度_交互": 19.607280739216527,
      "到中心_欧式距离": 0.1431569359207108
    },
    "mins": {
      "经度": 115.05028667379976,
      "纬度": 39.10862576786905,
      "到市中心距离_km": 0.27102843783313,
      "区域编码": 0.0,
      "面积（m²）": 20.58,
      "室数": 1.0,
      "厅数": 1.0,
      "卫数": null,
      "总房间数": 2.0,
      "每室面积": 12.85,
      "总楼层数": 0.0,
      "当前楼层估算": 0.6000000000000001,
      "楼层比例": 0.2,
      "朝向评分": 1.0,
      "房龄": 7.0,
      "小区面积_数值": 2.0,
      "小区户数_数值": 2.0,
      "容积率_数值": 0.28,
      "绿化率_数值": 10.0,
      "物业费_数值": 0.0,
      "area_encoded": 0.0,
      "面积_平方": 423.53639999999996,
      "面积_立方": 8716.379111999999,
      "面积_平方根": 4.536518488885502,
      "面积_对数": 3.0717669598299886,
      "面积_小户型": 0.0,
      "面积_中户型": 0.0,
      "面积_大户型": 0.0,
      "面积_豪宅": 0.0,
      "距离_平方": 0.07345641411426683,
      "距离_倒数": 0.0011796954899022185,
      "距离_对数": 0.23982636633398527,
      "距离_核心区": 0.0,
      "距离_内环": 0.0,
      "距离_中环": 0.0,
      "距离_外环": 0.0,
      "房龄_平方": 49.0,
      "房龄_对数": 2.0794415416798357,
      "房龄_次新房": 0.0,
      "房龄_较新": 0.0,
      "房龄_中等": 0.0,
      "房龄_老旧": 0.0,
      "面积_距离_交互": 23.501594788528852,
      "面积_距离倒数_交互": 0.07409667372075834,
      "面积对数_距离对数_交互": 1.1116466045078055,
      "面积_房龄_交互": 185.21999999999997,
      "面积对数_房龄对数_交互": 7.073004810856172,
      "距离_房龄_交互": 15.872103747788069,
      "面积_距离_房龄_三维交互": 517.0350853476348,
      "户型_室厅比": 0.25,
      "户型_厅室和": 2.0,
      "楼层_中间度": 0.30000000000000004,
      "楼层_顶底惩罚": 0.0,
      "楼层_黄金层": 0.0,
      "小区品质_综合": 2.132895816242822,
      "经纬度_交互": 4551.685662226725,
      "到中心_欧式距离": 0.002070312112296164
    },
    "maxs": {
      "经度": 117.17570424377308,
      "纬度": 47.52662451,
      "到市中心距离_km": 847.576377980293,
      "区域编码": 21.0,
      "面积（m²）": 499.13,
      "室数": 9.0,
      "厅数": 4.0,
      "卫数": null,
      "总房间数": 11.0,
      "每室面积": 263.66,
      "总楼层数": 41.0,
      "当前楼层估算": 28.8,
      "楼层比例": 0.8000000000000002,
      "朝向评分": 5.0,
      "房龄": 72.0,
      "小区面积_数值": 760000000.0,
      "小区户数_数值": 135263.0,
      "容积率_数值": 12.09,
      "绿化率_数值": 80.0,
      "物业费_数值": 19.0,
      "area_encoded": 21.0,
      "面积_平方": 249130.7569,
      "面积_立方": 124348634.691497,
      "面积_平方根": 22.341217513824084,
      "面积_对数": 6.21486806462805,
      "面积_小户型": 1.0,
      "面积_中户型": 1.0,
      "面积_大户型": 1.0,
      "面积_豪宅": 1.0,
      "距离_平方": 718385.7165101926,
      "距离_倒数": 2.695211196856425,
      "距离_对数": 6.743560095921077,
      "距离_核心区": 1.0,
      "距离_内环": 1.0,
      "距离_中环": 1.0,
      "距离_外环": 1.0,
      "房龄_平方": 5184.0,
      "房龄_对数": 4.290459441148391,
      "房龄_次新房": 0.0,
      "房龄_较新": 1.0,
      "房龄_中等": 1.0,
      "房龄_老旧": 1.0,
      "面积_距离_交互": 87427.50338866723,
      "面积_距离倒数_交互": 318.46615502055516,
      "面积对数_距离对数_交互": 31.329448418495314,
      "面积_房龄_交互": 12745.34,
      "面积对数_房龄对数_交互": 21.172865891276214,
      "距离_房龄_交互": 2290.4219322042154,
      "面积_距离_房龄_三维交互": 438756.2819260986,
      "户型_室厅比": 4.5,
      "户型_厅室和": 11.0,
      "楼层_中间度": 0.9761904761904762,
      "楼层_顶底惩罚": 0.0,
      "楼层_黄金层": 1.0,
      "小区品质_综合": 137.2549019607843,
      "经纬度_交互": 5533.378466921848,
      "到中心_欧式距离": 7.626672016972904
    }
  }
}